visafx/__init__.py
visafx/rates.py
visafx/test_rates.py
visafx-0.1.5.dist-info/LICENSE
visafx-0.1.5.dist-info/METADATA
visafx-0.1.5.dist-info/WHEEL
visafx-0.1.5.dist-info/RECORD
