Metadata-Version: 2.1
Name: visafx
Version: 0.1.5
Summary: 
Author: なるみ
Author-email: toucans-cutouts0f@icloud.com
Requires-Python: >=3.9,<4.0
Classifier: Programming Language :: Python :: 3
Classifier: Programming Language :: Python :: 3.9
Classifier: Programming Language :: Python :: 3.10
Classifier: Programming Language :: Python :: 3.11
Requires-Dist: cloudscraper (>=1.2.71,<2.0.0)
Requires-Dist: loguru (>=0.7.0,<0.8.0)
Requires-Dist: pydantic (>=1.10.9,<2.0.0)
Requires-Dist: retry (>=0.9.2,<0.10.0)
